bhavpr/__init__.py
bhavpr/proxy.py
bhavpr/collection/__init__.py
bhavpr/collection/constants.py
bhavpr/collection/download_helper.py
bhavpr/collection/fetch_pr.py
bhavpr/collection/logger_factory.py
bhavpr/parser/__init__.py
bhavpr/parser/anddmmyy.py
bhavpr/parser/bcddmmyy.py
bhavpr/parser/bhddmmyy.py
bhavpr/parser/bmddmmyy.py
bhavpr/parser/company.py
bhavpr/parser/pr_record.py
bhavpr-1.0.0.dist-info/LICENSE
bhavpr-1.0.0.dist-info/METADATA
bhavpr-1.0.0.dist-info/WHEEL
bhavpr-1.0.0.dist-info/top_level.txt
bhavpr-1.0.0.dist-info/RECORD
