Metadata-Version: 2.1
Name: bhavpr
Version: 1.0.0
Summary: A simple parser to consume PR files available with NSE.
Home-page: https://github.com/jcopps/BhavCopyPRParser
Author: Jeffry Copps Robert Jose
Author-email: code.jeffry@gmail.com
License: UNKNOWN
Platform: UNKNOWN
Classifier: Programming Language :: Python :: 3
Classifier: License :: OSI Approved :: MIT License
Classifier: Operating System :: OS Independent
Requires-Python: >=3.5
Requires-Dist: requests (==2.25.1)
Requires-Dist: appdirs (==1.4.4)
